{
	"biz_id": "threerivers",
	"deal_tokens": [ "trc-cc-gift-register","trc-cc-gift-rsvp" ],
	"most_recent_only": true, # omit or set to false for all rows
	
	"as_xlsx": false, # omit or set to false for default (CSV)

#	The following column values are always available (attrib):
#	
#	_when		grab timestamp (Unix -- for now)
#	_mobile		User mobile number
#	_deal		Deal token
#	_rowid		unique row (grab) identifier

	"COLUMNS": [
		{
			"column_name": "Row ID",
			"attrib": "_rowid"
		},
		{
			"column_name": "Timestamp",
			"attrib": "_when"
		},
		{
			"column_name": "Mobile",
			"attrib": "_mobile"
		},
		{
			"column_name": "Deal ID",
			"attrib": "_deal"
		},
		{
			"column_name": "Player ID",
			"attrib": "PlayerID"
		},
		{
			"column_name": "Last Name",
			"attrib": "z_LASTNAME"
		},
		{
			"column_name": "First Name",
			"attrib": "z_FIRSTNAME"
		},
		{
			"column_name": "Attending",
			"attrib": "attend"
		},
		{
			"column_name": "Day",
			"attrib": "day"
		},
		{
			"column_name": "Time",
			"attrib": "time"
		},
		{
			"column_name": "Gift",
			"attrib": "gift"
		},
		{
			"column_name": "Initials",
			"attrib": "initials"
		},
		{
			"column_name": "Room",
			"attrib": "room"
		},
		{
			"column_name": "Address",
			"attrib": "address"
		},
		{
			"column_name": "City",
			"attrib": "city"
		},
		{
			"column_name": "State",
			"attrib": "state"
		},
		{
			"column_name": "Zip",
			"attrib": "zip"
		}
	]
}
