{
	"notify": {
		"text": "From Albert G's: BBQ pro! You’ve hit 10 visits and earned 10% off your next bill. Don’t forget to scan the QR at your table on your next visit to check-in and unlock your discount."
	},
	"redeem_button": {
		"text": "10% discount!"
	},
	"redeem_confirm": {
		"header": "Confirm",
		"text": "Are you ready to redeem this reward? (10%)"
	},
	"reward": {
		"header": "10% Discount!",
		"text": "Just show this to your server to redeem your **10% discount!**"
#	},
#	"valid": {
#		"start_offset": 1 # next day
	}
}
